id_roles/__init__.py
id_roles/roles.py
id_roles-0.0.6.dist-info/LICENSE
id_roles-0.0.6.dist-info/METADATA
id_roles-0.0.6.dist-info/WHEEL
id_roles-0.0.6.dist-info/top_level.txt
id_roles-0.0.6.dist-info/RECORD
