Metadata-Version: 2.1
Name: id-roles
Version: 0.0.6
Summary: Id-manager roles package
Home-page: https://github.com/W-DEJONG/id-roles
Author: Wouter de Jong
Author-email: author@example.com
License: UNKNOWN
Platform: UNKNOWN
Classifier: Programming Language :: Python :: 3
Classifier: License :: OSI Approved :: MIT License
Classifier: Operating System :: OS Independent
Classifier: Development Status :: 4 - Beta
Classifier: Topic :: Security
Requires-Python: >=3.6
